Metadata-Version: 2.1
Name: mcko
Version: 0.0
Summary: Gaussian and Binomial distributions
Author-email: gif1601@mail.ru
License: UNKNOWN
Platform: UNKNOWN
